send_mail.py
send_mail-0.0.2.dist-info/LICENSE.txt
send_mail-0.0.2.dist-info/METADATA
send_mail-0.0.2.dist-info/WHEEL
send_mail-0.0.2.dist-info/top_level.txt
send_mail-0.0.2.dist-info/RECORD
