Metadata-Version: 2.1
Name: send-mail
Version: 0.0.2
Summary: Sending emails in python just became much easier
Home-page: https://github.com/farhadzaidi/send_mail
Author: Farhad Zaidi
Author-email: zaidi.farhad03@gmail.com
License: UNKNOWN
Platform: UNKNOWN
Classifier: Programming Language :: Python :: 3.6
Classifier: Programming Language :: Python :: 3.7
Classifier: Programming Language :: Python :: 3.8
Classifier: License :: OSI Approved :: GNU General Public License v2 or later (GPLv2+)
Classifier: Operating System :: OS Independent
Requires-Dist: easy-colors
